{
    "customers": [
        {"id":1,"name":"Argyle","email":"margyle0@ocn.ne.jp","password":"pargyle0@pbs.org"},
        {"id":2,"name":"Blesli","email":"ablesli1@hhs.gov","password":"mblesli1@hc360.com"},
        {"id":3,"name":"MacTague","email":"bmactague2@forbes.com","password":"amactague2@instagram.com"},
        {"id":4,"name":"McDermott-Row","email":"jmcdermottrow3@typepad.com","password":"jmcdermottrow3@angelfire.com"},
        {"id":5,"name":"Merigon","email":"gmerigon4@intel.com","password":"pmerigon4@msu.edu"},
        {"id":6,"name":"Thatcham","email":"wthatcham5@disqus.com","password":"lthatcham5@msu.edu"},
        {"id":7,"name":"Pilsbury","email":"rpilsbury6@japanpost.jp","password":"tpilsbury6@twitter.com"},
        {"id":8,"name":"Janway","email":"kjanway7@storify.com","password":"cjanway7@yellowbook.com"},
        {"id":9,"name":"Reynolds","email":"creynolds8@spiegel.de","password":"wreynolds8@auda.org.au"},
        {"id":10,"name":"Heisham","email":"lheisham9@trellian.com","password":"aheisham9@mysql.com"},
        {"id":11,"name":"Bereford","email":"bbereforda@usgs.gov","password":"cbereforda@ovh.net"},
        {"id":12,"name":"Fairbank","email":"kfairbankb@businessweek.com","password":"rfairbankb@github.com"},
        {"id":13,"name":"Kauschke","email":"kkauschkec@tumblr.com","password":"ckauschkec@bloomberg.com"},
        {"id":14,"name":"Strodder","email":"bstrodderd@washington.edu","password":"wstrodderd@dailymotion.com"},
        {"id":15,"name":"Harefoot","email":"charefoote@msu.edu","password":"bharefoote@deliciousdays.com"},
        {"id":16,"name":"Reynard","email":"freynardf@nih.gov","password":"wreynardf@hao123.com"},
        {"id":17,"name":"Treacy","email":"rtreacyg@home.pl","password":"mtreacyg@amazon.co.jp"},
        {"id":18,"name":"Rushmare","email":"hrushmareh@clickbank.net","password":"hrushmareh@google.fr"},
        {"id":19,"name":"Castelletto","email":"scastellettoi@jiathis.com","password":"rcastellettoi@elpais.com"},
        {"id":20,"name":"Guillerman","email":"sguillermanj@cnn.com","password":"bguillermanj@home.pl"},
        {"id":21,"name":"Gentzsch","email":"lgentzschk@ftc.gov","password":"jgentzschk@canalblog.com"},
        {"id":22,"name":"Scapelhorn","email":"rscapelhornl@upenn.edu","password":"lscapelhornl@tinyurl.com"},
        {"id":23,"name":"Huddle","email":"chuddlem@1688.com","password":"ehuddlem@vinaora.com"},
        {"id":24,"name":"Hillborne","email":"phillbornen@weibo.com","password":"phillbornen@naver.com"},
        {"id":25,"name":"Sabban","email":"fsabbano@usgs.gov","password":"rsabbano@rakuten.co.jp"},
        {"id":26,"name":"Sture","email":"esturep@rakuten.co.jp","password":"asturep@amazonaws.com"},
        {"id":27,"name":"Guilloud","email":"aguilloudq@ibm.com","password":"bguilloudq@baidu.com"},
        {"id":28,"name":"Rayman","email":"craymanr@answers.com","password":"araymanr@statcounter.com"},
        {"id":29,"name":"Spark","email":"ksparks@istockphoto.com","password":"hsparks@zimbio.com"},
        {"id":30,"name":"Loftin","email":"jloftint@moonfruit.com","password":"dloftint@seesaa.net"},
        {"id":31,"name":"Shane","email":"tshaneu@exblog.jp","password":"dshaneu@hatena.ne.jp"},
        {"id":32,"name":"Bemrose","email":"bbemrosev@flavors.me","password":"lbemrosev@pen.io"},
        {"id":33,"name":"de Keyser","email":"jdekeyserw@whitehouse.gov","password":"bdekeyserw@xing.com"},
        {"id":34,"name":"Soppit","email":"bsoppitx@gnu.org","password":"gsoppitx@ameblo.jp"},
        {"id":35,"name":"Rivelin","email":"criveliny@shareasale.com","password":"lriveliny@accuweather.com"},
        {"id":36,"name":"Franciottoi","email":"wfranciottoiz@foxnews.com","password":"vfranciottoiz@hugedomains.com"},
        {"id":37,"name":"Carlesi","email":"rcarlesi10@trellian.com","password":"tcarlesi10@google.de"},
        {"id":38,"name":"Miettinen","email":"mmiettinen11@umn.edu","password":"bmiettinen11@squidoo.com"},
        {"id":39,"name":"Rieme","email":"rrieme12@mediafire.com","password":"brieme12@dedecms.com"},
        {"id":40,"name":"Eatock","email":"deatock13@tinypic.com","password":"jeatock13@chron.com"},
        {"id":41,"name":"Furley","email":"wfurley14@techcrunch.com","password":"lfurley14@wikimedia.org"},
        {"id":42,"name":"Tremouille","email":"mtremouille15@mashable.com","password":"atremouille15@microsoft.com"},
        {"id":43,"name":"Goor","email":"sgoor16@mayoclinic.com","password":"cgoor16@lulu.com"},
        {"id":44,"name":"Capstaff","email":"dcapstaff17@va.gov","password":"dcapstaff17@ucsd.edu"},
        {"id":45,"name":"Smitton","email":"msmitton18@fda.gov","password":"esmitton18@java.com"},
        {"id":46,"name":"Rainbird","email":"vrainbird19@spotify.com","password":"prainbird19@godaddy.com"},
        {"id":47,"name":"Pescud","email":"rpescud1a@com.com","password":"dpescud1a@java.com"},
        {"id":48,"name":"Goodenough","email":"egoodenough1b@china.com.cn","password":"fgoodenough1b@reverbnation.com"},
        {"id":49,"name":"Dobinson","email":"bdobinson1c@discovery.com","password":"ldobinson1c@chronoengine.com"},
        {"id":50,"name":"Beeze","email":"gbeeze1d@ustream.tv","password":"hbeeze1d@statcounter.com"},
        {"id":51,"name":"Clausen","email":"cclausen1e@friendfeed.com","password":"cclausen1e@netscape.com"},
        {"id":52,"name":"Rockey","email":"brockey1f@wufoo.com","password":"krockey1f@vistaprint.com"},
        {"id":53,"name":"Jimmison","email":"djimmison1g@prweb.com","password":"mjimmison1g@flavors.me"},
        {"id":54,"name":"De Bruijne","email":"zdebruijne1h@rakuten.co.jp","password":"mdebruijne1h@youtu.be"},
        {"id":55,"name":"Apfler","email":"capfler1i@biblegateway.com","password":"sapfler1i@domainmarket.com"},
        {"id":56,"name":"Gladwish","email":"rgladwish1j@businessinsider.com","password":"fgladwish1j@army.mil"},
        {"id":57,"name":"Rizzillo","email":"mrizzillo1k@amazon.co.jp","password":"hrizzillo1k@alexa.com"},
        {"id":58,"name":"Blackster","email":"lblackster1l@infoseek.co.jp","password":"rblackster1l@spotify.com"},
        {"id":59,"name":"Fahy","email":"cfahy1m@vinaora.com","password":"mfahy1m@sciencedirect.com"},
        {"id":60,"name":"Whardley","email":"gwhardley1n@dailymotion.com","password":"pwhardley1n@purevolume.com"},
        {"id":61,"name":"Samson","email":"rsamson1o@state.tx.us","password":"ksamson1o@google.co.jp"},
        {"id":62,"name":"Teodori","email":"lteodori1p@networkadvertising.org","password":"kteodori1p@newyorker.com"},
        {"id":63,"name":"Helkin","email":"mhelkin1q@newyorker.com","password":"jhelkin1q@pcworld.com"},
        {"id":64,"name":"Hryniewicz","email":"ghryniewicz1r@sakura.ne.jp","password":"dhryniewicz1r@shareasale.com"},
        {"id":65,"name":"Whinray","email":"awhinray1s@prnewswire.com","password":"cwhinray1s@amazonaws.com"},
        {"id":66,"name":"Southall","email":"jsouthall1t@wsj.com","password":"dsouthall1t@dmoz.org"},
        {"id":67,"name":"Durran","email":"mdurran1u@yahoo.co.jp","password":"mdurran1u@dyndns.org"},
        {"id":68,"name":"Teaser","email":"cteaser1v@hostgator.com","password":"cteaser1v@odnoklassniki.ru"},
        {"id":69,"name":"Fairall","email":"bfairall1w@springer.com","password":"kfairall1w@sina.com.cn"},
        {"id":70,"name":"Tysall","email":"itysall1x@amazon.com","password":"mtysall1x@tripadvisor.com"},
        {"id":71,"name":"Diess","email":"jdiess1y@ow.ly","password":"tdiess1y@mapquest.com"},
        {"id":72,"name":"Colling","email":"hcolling1z@qq.com","password":"lcolling1z@cnn.com"},
        {"id":73,"name":"Overland","email":"ioverland20@sciencedirect.com","password":"aoverland20@noaa.gov"},
        {"id":74,"name":"Gregorin","email":"bgregorin21@cdbaby.com","password":"cgregorin21@apache.org"},
        {"id":75,"name":"Solan","email":"esolan22@yolasite.com","password":"vsolan22@nymag.com"},
        {"id":76,"name":"Raithbie","email":"graithbie23@economist.com","password":"jraithbie23@time.com"},
        {"id":77,"name":"Deniscke","email":"ldeniscke24@cargocollective.com","password":"ddeniscke24@surveymonkey.com"},
        {"id":78,"name":"Jekel","email":"wjekel25@microsoft.com","password":"fjekel25@gnu.org"},
        {"id":79,"name":"Rustedge","email":"lrustedge26@jigsy.com","password":"arustedge26@mail.ru"},
        {"id":80,"name":"Barense","email":"cbarense27@drupal.org","password":"lbarense27@dropbox.com"},
        {"id":81,"name":"Bowskill","email":"mbowskill28@youtu.be","password":"ybowskill28@amazon.co.uk"},
        {"id":82,"name":"De Ambrosis","email":"ideambrosis29@weibo.com","password":"sdeambrosis29@chron.com"},
        {"id":83,"name":"Couvert","email":"hcouvert2a@unesco.org","password":"hcouvert2a@sciencedirect.com"},
        {"id":84,"name":"Soars","email":"psoars2b@rambler.ru","password":"bsoars2b@sciencedirect.com"},
        {"id":85,"name":"Smy","email":"tsmy2c@bloglovin.com","password":"gsmy2c@wp.com"},
        {"id":86,"name":"Bryde","email":"ebryde2d@shop-pro.jp","password":"fbryde2d@nhs.uk"},
        {"id":87,"name":"Haigh","email":"fhaigh2e@illinois.edu","password":"fhaigh2e@livejournal.com"},
        {"id":88,"name":"Bagnell","email":"wbagnell2f@google.es","password":"tbagnell2f@geocities.com"},
        {"id":89,"name":"Dakhov","email":"ndakhov2g@jugem.jp","password":"pdakhov2g@loc.gov"},
        {"id":90,"name":"Kindred","email":"akindred2h@ucla.edu","password":"mkindred2h@prnewswire.com"},
        {"id":91,"name":"Skerm","email":"askerm2i@sun.com","password":"cskerm2i@barnesandnoble.com"},
        {"id":92,"name":"Simcoe","email":"hsimcoe2j@blogtalkradio.com","password":"asimcoe2j@google.it"},
        {"id":93,"name":"Swinford","email":"rswinford2k@technorati.com","password":"cswinford2k@shinystat.com"},
        {"id":94,"name":"Yetman","email":"pyetman2l@dagondesign.com","password":"myetman2l@elegantthemes.com"},
        {"id":95,"name":"Laden","email":"jladen2m@wordpress.com","password":"rladen2m@zdnet.com"},
        {"id":96,"name":"Gallifont","email":"cgallifont2n@pinterest.com","password":"agallifont2n@skype.com"},
        {"id":97,"name":"Kinningley","email":"kkinningley2o@umich.edu","password":"dkinningley2o@newyorker.com"},
        {"id":98,"name":"Woodhams","email":"swoodhams2p@instagram.com","password":"awoodhams2p@symantec.com"},
        {"id":99,"name":"Dansken","email":"ldansken2q@google.ru","password":"edansken2q@ovh.net"},
        {"id":100,"name":"Bowlas","email":"cbowlas2r@illinois.edu","password":"qbowlas2r@webmd.com"}
    ]
  
  }